LICENSE
MANIFEST.in
python-copr-common.spec
run_tests.sh
setup.py
copr_common/__init__.py
copr_common/background_worker.py
copr_common/compat.py
copr_common/dispatcher.py
copr_common/enums.py
copr_common/helpers.py
copr_common/lock.py
copr_common/log.py
copr_common/redis_helpers.py
copr_common/request.py
copr_common/rpm.py
copr_common/subprocess_live_output.py
copr_common/tree.py
copr_common/worker_manager.py
copr_common.egg-info/PKG-INFO
copr_common.egg-info/SOURCES.txt
copr_common.egg-info/dependency_links.txt
copr_common.egg-info/not-zip-safe
copr_common.egg-info/requires.txt
copr_common.egg-info/top_level.txt
tests/test_popen_live_output.py
tests/test_request.py