Metadata-Version: 2.1
Name: copr-common
Version: 1.2
Summary: Common python code used by Copr.
Home-page: https://github.com/fedora-copr/copr
Author: Dominik Turecek
Author-email: dturecek@redhat.com
License: GPLv2+
License-File: LICENSE
Requires-Dist: filelock
Requires-Dist: setproctitle
